{
    "root": ["GET", "/"],
    "metrics": ["GET", "/metrics"],
    "namespaces": ["GET", "/api/v1/namespaces/{name}"],
    "pods": ["GET", "/api/v1/namespaces/{namespace}/pods/{name}"],
    "secrets": ["GET", "/api/v1/namespaces/{namespace}/secrets/{name}"],
    "serviceaccounts": ["GET", "/api/v1/namespaces/{namespace}/serviceaccounts/{name}"],
    "services": ["GET", "/api/v1/namespaces/{namespace}/services/{name}"],
    "roles": ["GET", "/apis/rbac.authorization.k8s.io/v1/namespaces/{namespace}/roles/{name}"],
    "rolebindings": ["GET", "/apis/rbac.authorization.k8s.io/v1/namespaces/{namespace}/rolebindings/{name}"],
    "clusterroles": ["GET", "/apis/rbac.authorization.k8s.io/v1/clusterroles/{name}"],
    "clusterrolebindings": ["GET", "/apis/rbac.authorization.k8s.io/v1/clusterrolebindings/{name}"]
}